saf3ai_sdk/__init__.py
saf3ai_sdk/adk_callbacks.py
saf3ai_sdk/callbacks.py
saf3ai_sdk/scanner.py
saf3ai_sdk/client/__init__.py
saf3ai_sdk/client/client.py
saf3ai_sdk/config/__init__.py
saf3ai_sdk/config/config.py
saf3ai_sdk/core/__init__.py
saf3ai_sdk/core/auth.py
saf3ai_sdk/core/tracer.py
saf3ai_sdk/core/decorators/__init__.py
saf3ai_sdk/core/decorators/decorators.py
saf3ai_sdk/core/exporters/__init__.py
saf3ai_sdk/core/exporters/console_exporter.py
saf3ai_sdk/core/exporters/opensearch_exporter.py
saf3ai_sdk/frameworks/FRAMEWORK_ADAPTER_TEMPLATE.py
saf3ai_sdk/frameworks/README.md
saf3ai_sdk/frameworks/__init__.py
saf3ai_sdk/frameworks/adk.py
saf3ai_sdk/frameworks/ag2_adapter.py
saf3ai_sdk/frameworks/ai21_adapter.py
saf3ai_sdk/frameworks/anthropic_adapter.py
saf3ai_sdk/frameworks/base.py
saf3ai_sdk/frameworks/camelai_adapter.py
saf3ai_sdk/frameworks/cohere_adapter.py
saf3ai_sdk/frameworks/crewai_adapter.py
saf3ai_sdk/frameworks/groq_adapter.py
saf3ai_sdk/frameworks/haystack_adapter.py
saf3ai_sdk/frameworks/langchain.py
saf3ai_sdk/frameworks/langflow_adapter.py
saf3ai_sdk/frameworks/litellm_adapter.py
saf3ai_sdk/frameworks/llamaindex_adapter.py
saf3ai_sdk/frameworks/llamastack_adapter.py
saf3ai_sdk/frameworks/mistral_adapter.py
saf3ai_sdk/frameworks/multion_adapter.py
saf3ai_sdk/frameworks/ollama_adapter.py
saf3ai_sdk/frameworks/openai_adapter.py
saf3ai_sdk/frameworks/rest_adapter.py
saf3ai_sdk/frameworks/smolagents_adapter.py
saf3ai_sdk/frameworks/swarmzero_adapter.py
saf3ai_sdk/frameworks/taskweaver_adapter.py
saf3ai_sdk/frameworks/xai_adapter.py
saf3ai_sdk/instrumentation/__init__.py
saf3ai_sdk/instrumentation/adk_instrumentation.py
saf3ai_sdk/instrumentation/anthropic_instrumentation.py
saf3ai_sdk/instrumentation/crewai_instrumentation.py
saf3ai_sdk/instrumentation/langchain_instrumentation.py
saf3ai_sdk/instrumentation/litellm_instrumentation.py
saf3ai_sdk/instrumentation/llamaindex_instrumentation.py
saf3ai_sdk/instrumentation/llm_providers_instrumentation.py
saf3ai_sdk-0.2.2.dist-info/METADATA
saf3ai_sdk-0.2.2.dist-info/WHEEL
saf3ai_sdk-0.2.2.dist-info/licenses/LICENSE
saf3ai_sdk-0.2.2.dist-info/RECORD
