Metadata-Version: 2.4
Name: saf3ai-sdk
Version: 0.2.2
Summary: Observability and Telemetry SDK for AI Agents with Local Storage
Project-URL: Github, https://github.com/saf3ai/saf3ai_sdk
Project-URL: PyPI, https://pypi.org/project/saf3ai-sdk/
Author-email: Saf3AI Team <team@saf3ai.com>
License-File: LICENSE
Classifier: License :: OSI Approved :: MIT License
Classifier: Operating System :: OS Independent
Classifier: Programming Language :: Python :: 3
Classifier: Programming Language :: Python :: 3.9
Classifier: Programming Language :: Python :: 3.10
Classifier: Programming Language :: Python :: 3.11
Classifier: Programming Language :: Python :: 3.12
Requires-Python: >=3.9
Requires-Dist: opentelemetry-api>=1.20.0
Requires-Dist: opentelemetry-exporter-otlp-proto-grpc>=1.20.0
Requires-Dist: opentelemetry-exporter-otlp-proto-http>=1.20.0
Requires-Dist: opentelemetry-instrumentation>=0.40b0
Requires-Dist: opentelemetry-sdk>=1.20.0
Requires-Dist: opentelemetry-semantic-conventions>=0.40b0
Requires-Dist: packaging<25.0,>=21.0
Requires-Dist: psutil<7.0.0,>=5.9.0
Requires-Dist: pyyaml<7.0,>=6.0
Requires-Dist: requests<3.0.0,>=2.28.0
Requires-Dist: termcolor<2.5.0,>=2.3.0
Requires-Dist: wrapt<2.0.0,>=1.14.0
Provides-Extra: dev
Requires-Dist: black>=22.0.0; extra == 'dev'
Requires-Dist: isort>=5.10.0; extra == 'dev'
Requires-Dist: mypy>=1.0.0; extra == 'dev'
Requires-Dist: pytest-asyncio>=0.21.0; extra == 'dev'
Requires-Dist: pytest-mock>=3.10.0; extra == 'dev'
Requires-Dist: pytest>=7.0.0; extra == 'dev'
Requires-Dist: ruff>=0.1.0; extra == 'dev'
